{
  "author": "K.A. Applegate",
  "id": "111",
  "description": "We could blame everything that happened on Marco. He was the one who heard about the downed submarine. He was the one who thought we should check it out. And everyone knows that if Marco's up to a challenge, I'm definitely there.Everything was going fine. Until the explosion. An explosion that blows us millions of years back in time. Back to the age of dinosaurs. Now Tobias, Cassie, Marco, Ax, Jake and I are fighting for our lives with every step we take. But that's not our biggest problem. Our biggest problem is we have no idea how to get back to our own time ...",
  "editions": [
    "english",
    "spanish",
    "french"
  ],
  "genres": [
    "adventure",
    "animals",
    "childrens",
    "childrens (middle grade)",
    "fantasy",
    "fiction",
    "science fiction",
    "science fiction (aliens)",
    "science fiction (time travel)",
    "young adult"
  ],
  "inventory": [
    {
      "status": "available",
      "stock_id": "111_1"
    }
  ],
  "metrics": {
    "rating_votes": 2511,
    "score": 3.84
  },
  "pages": 774,
  "title": "In the Time of Dinosaurs",
  "url": "https://www.goodreads.com/book/show/363363.In_the_Time_of_Dinosaurs",
  "year_published": 1998
}
