{
    "author": "Jodi Taylor",
    "id": "174",
    "description": "Here's a question for you. What's the most exciting thing ever found in a fire bucket? And don't say 'fire' because you'll be wrong.  Suppose - just suppose - it was the technology to take a pod to Mars? Yeah, now we're talking!  Every Christmas, for reasons which seem good at the time - especially after an eggnog or two - Max and the others leap into the nearest pod and indulge in their illegal Christmas jump. It's a tradition. This year, however, just to be different, they find themselves part of someone else's illegal Christmas jump. It's time to don a spacesuit and bring your own urine!",
    "editions": [
        "english",
        "spanish"
    ],
    "genres": {
        "adventure": 9,
        "audiobook": 12,
        "fantasy": 36,
        "fiction": 30,
        "historical (historical fiction)": 15,
        "humor": 8,
        "science fiction": 33,
        "science fiction (time travel)": 53,
        "science fiction fantasy": 7,
        "short stories": 17
    },
    "inventory": [
        {
            "status": "maintenance",
            "stock_id": "174_1"
        },
        {
            "status": "on_loan",
            "stock_id": "174_2"
        },
        {
            "status": "available",
            "stock_id": "174_3"
        },
        {
            "status": "on_loan",
            "stock_id": "174_4"
        }
    ],
    "metrics": {
        "rating_votes": 2070,
        "score": 4.38
    },
    "pages": 494,
    "title": "And Now For Something Completely Different",
    "url": "https://www.goodreads.com/book/show/42077017-and-now-for-something-completely-different",
    "year_published": 2018
}