{
    "author_name": "Zoey Draven",
    "base_id": 452,
    "book_description": "\nShe broke their laws. Now, he has come to punish her\u2026\nIn my human settlement on the hostile plains of Dakkar, I am an outcast, a strange girl orphaned since birth, alone, and dreaming of a life I don't have. I hunt to survive, though it is forbidden, though it breaks the strict Dakkari laws that we all must follow.When my desperate actions catch the attention of a Dakkari horde king\u2014a cold, powerful, and merciless warrior leader, with eyes like flint and a body like steel\u2014he seeks to punish me\u2026and he succeeds.But then he does the unexpected.Instead of taking my life, he claims me as his own.He steals me from my village and brings me back to his battle-bred horde. There, I warm his bed. I make bargains with him on starry, cold nights. I look into his grey eyes and see not a monster, but a demon king who captures my soul.But demons have a way of never letting go\u2026and as the cold season descends upon Dakkar, I begin to wonder if I even want him to, even when it hurts.Claimed by the Horde King is a full-length SFR novel (95,000+ words) with an HEA. It is the second book of the Horde Kings of Dakkar series.",
    "book_title": "Claimed by the Horde King",
    "editions": [
        "English"
    ],
    "genres": {
        "adult": 10,
        "aliens": 83,
        "erotica": 12,
        "fantasy": 55,
        "fantasy romance": 8,
        "paranormal": 34,
        "paranormal romance": 13,
        "romance": 78,
        "science fiction": 67,
        "science fiction romance": 23
    },
    "inventory": [
        {
            "status": "maintenance",
            "stock_number": "452_1"
        }
    ],
    "metrics": {
        "rating_votes": 3596,
        "score": 4.3
    },
    "original_book_title": "Claimed by the Horde King",
    "pages": 292,
    "url": "https://www.goodreads.com/book/show/49610915-claimed-by-the-horde-king",
    "year_published": 2019
}