{
  "author": "T. Michael Martin",
  "id": "498",
  "description": "It happened on Halloween.The world ended.And a dangerous Game brought it back to life.Seventeen-year-old Michael and his five-year-old brother, Patrick, have been battling monsters in The Game for weeks.In the rural mountains of West Virginia, armed with only their rifle and their love for each other, the brothers follow Instructions from the mysterious Game Master. They spend their days searching for survivors, their nights fighting endless hordes of “Bellows”—creatures that roam the dark, roaring for flesh. And at this Game, Michael and Patrick are very good.But The Game is changing.The Bellows are evolving.The Game Master is leading Michael and Patrick to other survivors—survivors who don’t play by the rules.And the brothers will never be the same.T. Michael Martin’s debut novel is a transcendent thriller filled with electrifying action, searing emotional insight, and unexpected romance.",
  "editions": [
    "english",
    "spanish",
    "french"
  ],
  "genres": [
    "apocalyptic (post apocalyptic)",
    "fantasy",
    "fantasy (paranormal)",
    "fiction",
    "horror",
    "horror (zombies)",
    "science fiction",
    "science fiction (apocalyptic)",
    "science fiction (dystopia)",
    "young adult"
  ],
  "inventory": [
    {
      "status": "available",
      "stock_id": "498_1"
    },
    {
      "status": "available",
      "stock_id": "498_2"
    },
    {
      "status": "on_loan",
      "stock_id": "498_3"
    },
    {
      "status": "on_loan",
      "stock_id": "498_4"
    },
    {
      "status": "on_loan",
      "stock_id": "498_5"
    },
    {
      "status": "available",
      "stock_id": "498_6"
    },
    {
      "status": "maintenance",
      "stock_id": "498_7"
    }
  ],
  "metrics": {
    "rating_votes": 3183,
    "score": 3.51
  },
  "pages": 1143,
  "title": "The End Games",
  "url": "https://www.goodreads.com/book/show/13228537-the-end-games",
  "year_published": 2013
}
