{
    "author": "Elizabeth Bear",
    "base_id": 527,
    "description": "Haimey Dz thinks she knows what she wants.She thinks she knows who she is.She is wrong.A routine salvage mission uncovers evidence of a terrible crime and relics of powerful ancient technology. Haimey and her small crew run afoul of pirates at the outer limits of the Milky Way, and find themselves on the run and in possession of universe-changing information.When authorities prove corrupt, Haimey realizes that she is the only one who can protect her galaxy-spanning civilization from the implications of this ancient technology\u2014and the revolutionaries who want to use it for terror and war. Her quest will take her careening from the event horizon of the supermassive black hole at the galaxy\u2019s core to the infinite, empty spaces at its edge.To save everything that matters, she will need to uncover the secrets of ancient intelligences lost to time\u2014and her own lost secrets, which she will wish had remained hidden from her forever.",
    "editions": [
        "English"
    ],
    "genres": {
        "adult": 14,
        "aliens": 19,
        "audiobook": 18,
        "fiction": 78,
        "lgbt": 46,
        "queer": 17,
        "science fiction": 333,
        "science fiction fantasy": 16,
        "space": 28,
        "space opera": 85
    },
    "inventory": [
        {
            "status": "maintenance",
            "stock_id": "527_1"
        },
        {
            "status": "available",
            "stock_id": "527_2"
        },
        {
            "status": "maintenance",
            "stock_id": "527_3"
        },
        {
            "status": "on_loan",
            "stock_id": "527_4"
        },
        {
            "status": "available",
            "stock_id": "527_5"
        }
    ],
    "metrics": {
        "rating_votes": 3187,
        "score": 3.78
    },
    "pages": 733,
    "title": "Ancestral Night",
    "url": "https://www.goodreads.com/book/show/26159745-ancestral-night",
    "year_published": 2019
}