{
  "author": "Nathan Van Coops",
  "id": "549",
  "description": "ASIN moved from less recent edition here\"We broke something. How do you break time? Can something so bad happen that you fracture the world?\" Benjamin Travers has been electrocuted. What's worse, he and his friends have woken up in the past. As the friends search for a way home, they realize they're not alone. There are other time travelers, and some of them are turning up dead. When Ben meets an enigmatic scientist and his charming, time-traveling daughter, salvation seems at hand, but escaping the dangers of the past may lead to a deadly future. If he hopes to save his friends, Ben must learn to master space and time, and survive a journey where past and future violently collide.",
  "editions": [
    "english",
    "spanish",
    "french"
  ],
  "genres": [
    "adventure",
    "apocalyptic (post apocalyptic)",
    "audiobook",
    "business (amazon)",
    "fantasy",
    "fiction",
    "mystery",
    "science fiction",
    "science fiction (time travel)",
    "science fiction fantasy"
  ],
  "inventory": [
    {
      "status": "on_loan",
      "stock_id": "549_1"
    },
    {
      "status": "maintenance",
      "stock_id": "549_2"
    }
  ],
  "metrics": {
    "rating_votes": 4862,
    "score": 3.99
  },
  "pages": 812,
  "title": "In Times Like These",
  "url": "https://www.goodreads.com/book/show/23444266-in-times-like-these",
  "year_published": 2013
}
