{
    "author": "Margaret Peterson Haddix",
    "id": "825",
    "description": "After helping Chip and Alex survive 15th century London, Jonah and Katherine are summoned to help another missing child, Andrea, face her fate. Andrea is really Virginia Dare, from the Lost Colony of Roanoke. Jonah and Katherine are confident in their ability to help Andrea fix history, but when their journey goes dangerously awry, they realize that they may be in over their head. They've landed in the wrong time period. Andrea doesn't seem that interested in leaving the past. And even worse, it appears that someone has deliberately sabotaged their mission...",
    "editions": [
        "english"
    ],
    "genres": {
        "adventure": 66,
        "childrens (middle grade)": 62,
        "fantasy": 92,
        "fiction": 73,
        "historical": 35,
        "historical (historical fiction)": 116,
        "mystery": 59,
        "science fiction": 189,
        "science fiction (time travel)": 117,
        "young adult": 118
    },
    "inventory": [
        {
            "status": "on_loan",
            "stock_id": "825_1"
        }
    ],
    "metrics": {
        "rating_votes": 11390,
        "score": 3.94
    },
    "pages": 713,
    "title": "Sabotaged",
    "url": "https://www.goodreads.com/book/show/7130745-sabotaged",
    "year_published": 2010
}